{
  "appId": "com.skkut.silkstack",
  "productName": "SilkStack Image Browser",
  "directories": {
    "output": "dist-electron"
  },
  "files": [
    "dist/**/*",
    "electron/**/*",
    "public/icon.ico",
    "public/SilkStack 1024.png",
    "public/SilkStack 512.png"
  ],
  "win": {
    "executableName": "SilkStack",
    "icon": "public/icon.ico",
    "target": [
      "nsis",
      "zip"
    ],
    "artifactName": "SilkStack-${version}-${os}-${arch}.${ext}",
    "cscLink": null,
    "cscKeyPassword": null
  },
  "mac": {
    "executableName": "SilkStack",
    "icon": "public/SilkStack 1024.png",
    "target": [
      {
        "target": "dmg",
        "arch": ["x64", "arm64"]
      }
    ],
    "category": "public.app-category.productivity",
    "entitlements": "build/entitlements.mac.plist",
    "entitlementsInherit": "build/entitlements.mac.plist",
    "hardenedRuntime": false,
    "gatekeeperAssess": false,
    "identity": null
  },
  "linux": {
    "executableName": "SilkStack",
    "icon": "public/SilkStack 512.png",
    "target": [
      {
        "target": "AppImage",
        "arch": ["x64"]
      }
    ],
    "category": "Utility",
    "synopsis": "Local image browser for AI generated images",
    "generateUpdatesFilesForAllChannels": true
  },
  "nsis": {
    "oneClick": false,
    "allowToChangeInstallationDirectory": true,
    "createDesktopShortcut": true,
    "createStartMenuShortcut": true,
    "artifactName": "SilkStack-Setup-${version}.${ext}"
  },
  "publish": {
    "provider": "github",
    "owner": "skkut",
    "repo": "SilkStack-Image-Browser",
    "releaseType": "release"
  },
  "generateUpdatesFilesForAllChannels": true
}
